<?xml version="1.0" encoding="UTF-8"?>
<!-- Do not edit values in <data> unless you know what you are doing -->
<data>
    <tile>
        <width>8</width>
        <height>8</height>
    </tile>
    <palette>
        <coloramount>16</coloramount>
    </palette>
    <bankheader>
        <address>0x02E80</address>
        <bankamount>14</bankamount>
    </bankheader>
    <bank>
        <paletteamount>15</paletteamount>
        <tileamount>1024</tileamount>
    </bank>
	<levelheader>
		<address>0xF298</address>
		<size>37</size>
		<levelamount>52</levelamount>
	</levelheader>
    <level>
        <tileamount>4096</tileamount>
        <tileindexsize>256</tileindexsize>
        <paletteindexamount>6</paletteindexamount>
    </level>
    <editortileset>
        <tileamount_width>16</tileamount_width>
        <tileamount_height>64</tileamount_height>
        <imagescaling>1</imagescaling>
    </editortileset>
    <editorcanvas>
        <tileamount_width>64</tileamount_width>
        <tileamount_height>64</tileamount_height>
        <imagescaling>1</imagescaling>
    </editorcanvas>
</data>